LICENSE
MANIFEST.in
setup.cfg
setup.py
examples/cp_sensory_bread_data.py
examples/rescal_kinships.py
scikit_tensor.egg-info/PKG-INFO
scikit_tensor.egg-info/SOURCES.txt
scikit_tensor.egg-info/dependency_links.txt
scikit_tensor.egg-info/top_level.txt
sktensor/__init__.py
sktensor/core.py
sktensor/cp.py
sktensor/dedicom.py
sktensor/dtensor.py
sktensor/indscal.py
sktensor/ktensor.py
sktensor/nn_asalsan.py
sktensor/parafac2.py
sktensor/pyutils.py
sktensor/rescal.py
sktensor/rescal3.py
sktensor/rotation.py
sktensor/setup.py
sktensor/sptensor.py
sktensor/tucker.py
sktensor/utils.py
sktensor/version.py
sktensor/tests/__init__.py
sktensor/tests/fixtures.py
sktensor/tests/test_base.py
sktensor/tests/test_dtensor.py
sktensor/tests/test_ktensor.py
sktensor/tests/test_pyutils.py
sktensor/tests/test_sptensor.py
sktensor/tests/test_tucker_hooi.py
sktensor/tests/test_utils.py