Metadata-Version: 1.1
Name: scikit-tensor
Version: 0.1
Summary: Python module for multilinear algebra and tensor factorizations
Home-page: http://github.com/mnick/scikit-tensor
Author: ('Maximilian Nickel',)
Author-email: mnick@mit.edu
License: GPLv3
Download-URL: http://github.com/mnick/scikit-tensor
Platform: UNKNOWN
Classifier: Development Status :: 3 - Alpha
Classifier: Intended Audience :: Developers
Classifier: Intended Audience :: Science/Research
Classifier: License :: OSI Approved :: GNU General Public License v3 (GPLv3)
Classifier: Topic :: Scientific/Engineering
Classifier: Topic :: Software Development
Classifier: Operating System :: Microsoft :: Windows
Classifier: Operating System :: POSIX
Classifier: Operating System :: Unix
Classifier: Operating System :: MacOS
Classifier: Programming Language :: Python :: 2
Classifier: Programming Language :: Python :: 2.6
Classifier: Programming Language :: Python :: 2.7
Classifier: Programming Language :: Python :: 3
Classifier: Programming Language :: Python :: 3.3
